{"de_inquiry.md":"BxBQNkko","fin_approve.md":"DSCna1kJ","fin_check.md":"msJcRzZ8","fin_confirm.md":"COBFOCw4","fin_inquiry.md":"WX7u1wfZ","fin_item.md":"eYuYJCu1","fin_price-list.md":"blPAvqcb","index.md":"BMecVB4j","mar_inquiry-new.md":"DYezENAO","mar_inquiry-onprocess.md":"BEZn0vQo","mar_inquiry-prebm.md":"BUe7h7Af","mar_inquiry-report.md":"CBUC8VNI","mar_inquiry-stock.md":"Bvqs_9l0","mar_master-control.md":"Jh-lbn6T","mar_master-cur.md":"BpQvtZ-U","mar_master-ratio.md":"2GCLFGZL","mar_orders.md":"Dy7fhw1T","mar_price-history.md":"B6WpwMhP","mar_price-item.md":"DkxUr_3E","mar_quotation-issue.md":"1dLTDFZM","mar_quotation-out.md":"DKYVgOOP","mar_quotation-release.md":"BrY5Cslh","mar_quotation-weight.md":"C0vtBL-D","pkc_inquiry.md":"Dkn99-aN","quick-start.md":"rIThOCVt","sale_inquiry.md":"DaYeDzdK"}
